ctgen/__init__.py
ctgen/__main__.py
ctgen/common.lua
ctgen/common.py
ctgen/dataset.py
ctgen/gen.py
ctgen_backends/cpp_iitrbd/__init__.py
ctgen_backends/cpp_iitrbd/backend.py
ctgen_backends/cpp_iitrbd/cmake_tpl.lua
ctgen_backends/cpp_iitrbd/config.py
ctgen_backends/cpp_iitrbd/config_table.lua
ctgen_backends/cpp_iitrbd/generator.lua
ctgen_backends/cpp_iitrbd/generator.py
ctgen_backends/cpp_iitrbd/header_tpl.lua
ctgen_backends/cpp_iitrbd/source_tpl.lua
ctgen_backends/cpp_iitrbd/tests_tpl.lua
ctgen_backends/octave/__init__.py
ctgen_backends/octave/backend.py
ctgen_backends/octave/config.lua
ctgen_backends/octave/config.py
ctgen_backends/octave/generator.lua
ctgen_backends/octave/generator.py
ctgen_backends/octave/tests_tpl.lua
ctgen-0.1.0.dist-info/LICENSE
ctgen-0.1.0.dist-info/METADATA
ctgen-0.1.0.dist-info/WHEEL
ctgen-0.1.0.dist-info/entry_points.txt
ctgen-0.1.0.dist-info/top_level.txt
ctgen-0.1.0.dist-info/RECORD
