Metadata-Version: 2.1
Name: ctgen
Version: 0.1.0
Summary: Coordinate-transforms code generator
Author-email: Marco Frigerio <marco.frigerio17@pm.me>
License: Copyright (c) 2020-2022, Marco Frigerio
Project-URL: home, https://github.com/mfrigerio17/ctgen
Requires-Python: >=3.4
License-File: LICENSE
Requires-Dist: numpy
Requires-Dist: sympy
Requires-Dist: lupa
Requires-Dist: pyyaml
Requires-Dist: kgprim
